rerun.me-1.0.0.dist-info/LICENSE.txt
rerun.me-1.0.0.dist-info/METADATA
rerun.me-1.0.0.dist-info/RECORD
rerun.me-1.0.0.dist-info/WHEEL
rerun.me-1.0.0.dist-info/top_level.txt
rerunme/__init__.py
