Metadata-Version: 2.1
Name: rerun.me
Version: 1.0.0
Summary: A library for rerunning erred functions with delays.
Home-page: https://github.com/jaredlgillespie/rerun.me
Author: Jared Gillespie
Author-email: jaredlgillespie@hotmail.com
License: MIT
Keywords: rerun.me rerun retry decorator
Platform: UNKNOWN
Classifier: Development Status :: 5 - Production/Stable
Classifier: Intended Audience :: Developers
Classifier: License :: OSI Approved :: MIT License
Classifier: Natural Language :: English
Classifier: Operating System :: OS Independent
Classifier: Programming Language :: Python :: 3
Classifier: Programming Language :: Python :: 3.4
Classifier: Programming Language :: Python :: 3.5
Classifier: Programming Language :: Python :: 3.6
Classifier: Programming Language :: Python :: Implementation :: CPython
Classifier: Topic :: Software Development :: Libraries :: Python Modules
Classifier: Topic :: Utilities
